{
  "properties": [
    {
      "name": "application.minio.endpoint",
      "defaultValue": "http://localhost:9000"
    },
    {
      "name": "application.minio.region",
      "defaultValue": "us-east-1"
    },
    {
      "name": "application.minio.sts-controller-enabled",
      "defaultValue": true
    },
    {
      "name": "application.minio.pre-signed-duration",
      "defaultValue": "10m"
    },
    {
      "name": "application.minio.sts-token-duration",
      "defaultValue": "10m"
    }
  ]
}